highresmodule/__init__.py
highresmodule/command_line.py
highresmodule/highres.py
highres-1.0.4.dist-info/LICENSE
highres-1.0.4.dist-info/METADATA
highres-1.0.4.dist-info/WHEEL
highres-1.0.4.dist-info/entry_points.txt
highres-1.0.4.dist-info/top_level.txt
highres-1.0.4.dist-info/RECORD
