Metadata-Version: 2.1
Name: highres
Version: 1.0.4
Summary: A script to download hi-resolution images using google search by image feature
Home-page: https://dillir07.github.io/highres/
Author: Dilli Babu R
Author-email: dillir07@outlook.com
License: UNKNOWN
Platform: UNKNOWN
Classifier: Programming Language :: Python :: 3
Classifier: Operating System :: OS Independent
Requires-Dist: selenium
